HISTORY.rst
HISTORY.txt
LICENSE.txt
MANIFEST.in
README.rst
README.txt
TODO.rst
requirements.txt
setup.py
sphinx_bootstrap_theme/__init__.py
sphinx_bootstrap_theme.egg-info/PKG-INFO
sphinx_bootstrap_theme.egg-info/SOURCES.txt
sphinx_bootstrap_theme.egg-info/dependency_links.txt
sphinx_bootstrap_theme.egg-info/requires.txt
sphinx_bootstrap_theme.egg-info/top_level.txt
sphinx_bootstrap_theme/bootstrap/globaltoc.html
sphinx_bootstrap_theme/bootstrap/layout.html
sphinx_bootstrap_theme/bootstrap/localtoc.html
sphinx_bootstrap_theme/bootstrap/navbar-2.html
sphinx_bootstrap_theme/bootstrap/navbar.html
sphinx_bootstrap_theme/bootstrap/navbarsearchbox.html
sphinx_bootstrap_theme/bootstrap/navbartoc.html
sphinx_bootstrap_theme/bootstrap/relations.html
sphinx_bootstrap_theme/bootstrap/search.html
sphinx_bootstrap_theme/bootstrap/searchbox.html
sphinx_bootstrap_theme/bootstrap/searchresults.html
sphinx_bootstrap_theme/bootstrap/sourcelink.html
sphinx_bootstrap_theme/bootstrap/theme.conf
sphinx_bootstrap_theme/bootstrap/static/bootstrap-sphinx.css_t
sphinx_bootstrap_theme/bootstrap/static/bootstrap-sphinx.js_t
sphinx_bootstrap_theme/bootstrap/static/bootstrap-2.3.2/css/bootstrap-responsive.css
sphinx_bootstrap_theme/bootstrap/static/bootstrap-2.3.2/css/bootstrap-responsive.min.css
sphinx_bootstrap_theme/bootstrap/static/bootstrap-2.3.2/css/bootstrap.css
sphinx_bootstrap_theme/bootstrap/static/bootstrap-2.3.2/css/bootstrap.min.css
sphinx_bootstrap_theme/bootstrap/static/bootstrap-2.3.2/img/glyphicons-halflings-white.png
sphinx_bootstrap_theme/bootstrap/static/bootstrap-2.3.2/img/glyphicons-halflings.png
sphinx_bootstrap_theme/bootstrap/static/bootstrap-2.3.2/js/bootstrap.js
sphinx_bootstrap_theme/bootstrap/static/bootstrap-2.3.2/js/bootstrap.min.js
sphinx_bootstrap_theme/bootstrap/static/bootstrap-3.3.7/css/bootstrap-theme.css
sphinx_bootstrap_theme/bootstrap/static/bootstrap-3.3.7/css/bootstrap-theme.css.map
sphinx_bootstrap_theme/bootstrap/static/bootstrap-3.3.7/css/bootstrap-theme.min.css
sphinx_bootstrap_theme/bootstrap/static/bootstrap-3.3.7/css/bootstrap-theme.min.css.map
sphinx_bootstrap_theme/bootstrap/static/bootstrap-3.3.7/css/bootstrap.css
