Metadata-Version: 1.1
Name: sphinx-bootstrap-theme
Version: 0.6.1
Summary: Sphinx Bootstrap Theme.
Home-page: http://ryan-roemer.github.com/sphinx-bootstrap-theme/README.html
Author: Ryan Roemer
Author-email: ryan@loose-bits.com
License: UNKNOWN
Platform: UNKNOWN
Classifier: Development Status :: 5 - Production/Stable
Classifier: Environment :: Web Environment
Classifier: Intended Audience :: Developers
Classifier: Intended Audience :: System Administrators
Classifier: License :: OSI Approved :: MIT License
Classifier: Operating System :: OS Independent
Classifier: Programming Language :: Python
Classifier: Topic :: Internet
Classifier: Topic :: Software Development :: Documentation
